pymex/VERSION
pymex/__init__.py
pymex/utils.py
pymex/clinvar/__init__.py
pymex/clinvar/record.py
pymex/egene/__init__.py
pymex/egene/record.py
pymex/mif/MIF254.xsd
pymex/mif/MIF300.xsd
pymex/mif/__init__.py
pymex/mif/builder.py
pymex/mif/defMif254.json
pymex/mif/defMif300.json
pymex/mif/defParse254.json
pymex/mif/defParse300.json
pymex/mif/interaction.py
pymex/mif/jmif-cvterm.jmif
pymex/mif/jmif-source.jmif
pymex/mif/record.py
pymex/mif/utils.py
pymex/mutilyzer/__init__.py
pymex/mutilyzer/record.py
pymex/pypsic/__init__.py
pymex/pypsic/psicregistry.py
pymex/pypsic/zclient.py
pymex/uniprot/__init__.py
pymex/uniprot/unirecord.py
pymex/up/__init__.py
pymex/up/defUniParse_v001.json
pymex/up/defUniXml_v001.json
pymex/up/unirecord.py
pymex/uparc/__init__.py
pymex/uparc/record.py
pymex/uprot/__init__.py
pymex/uprot/defUniParse_v001.json
pymex/uprot/defUniXml_v001.json
pymex/uprot/record.py
pymex/xmlrecord/__init__.py
pymex/xmlrecord/xmlrecord.py
pymex-0.9.31.dist-info/LICENSE
pymex-0.9.31.dist-info/METADATA
pymex-0.9.31.dist-info/WHEEL
pymex-0.9.31.dist-info/top_level.txt
pymex-0.9.31.dist-info/RECORD
