Metadata-Version: 2.1
Name: pymex
Version: 0.9.31
Summary: PYMEX: PSI-MI/IMEx Data Access
Home-page: https://github.com/IMExConsortium/pymex
Author: Pymex Support Group
Author-email: dip@mbi.ucla.edu
License: UNKNOWN
Download-URL: https://github.com/IMExConsortium/pymex/archive/0.9.31.tar.gz
Platform: UNKNOWN
Classifier: Programming Language :: Python :: 3
Classifier: License :: OSI Approved :: MIT License
Classifier: Operating System :: OS Independent
Classifier: Development Status :: 4 - Beta
Classifier: Topic :: Scientific/Engineering :: Bio-Informatics
Classifier: Intended Audience :: Science/Research
Requires-Python: >=3.5
Requires-Dist: lxml (>=3.5.0)
Requires-Dist: zeep (>=3.4)
